tsnecuda/TSNE.py
tsnecuda/__init__.py
tsnecuda/libtsnecuda.so
tsnecuda/test/__init__.py
tsnecuda-3.0.1.dist-info/LICENSE.txt
tsnecuda-3.0.1.dist-info/METADATA
tsnecuda-3.0.1.dist-info/WHEEL
tsnecuda-3.0.1.dist-info/top_level.txt
tsnecuda-3.0.1.dist-info/RECORD
