Metadata-Version: 2.1
Name: tsnecuda
Version: 3.0.1
Summary: CUDA Implementation of T-SNE with Python bindings
Home-page: https://github.com/CannyLab/tsne-cuda
Author: Chan, David M., Huang, Forrest., Rao, Roshan.
Author-email: davidchan@berkeley.edu
License: LICENSE.txt
Keywords: TSNE,CUDA,Machine Learning,AI
Platform: UNKNOWN
Classifier: Programming Language :: Python :: 3.6
Classifier: Programming Language :: Python :: 3.7
Classifier: Programming Language :: Python :: 3.8
Classifier: Programming Language :: Python :: 3.9
Classifier: Programming Language :: Python :: 3.10
Classifier: Operating System :: POSIX :: Linux
Classifier: Intended Audience :: Developers
Classifier: Intended Audience :: Science/Research
Classifier: Topic :: Scientific/Engineering :: Artificial Intelligence
Requires-Dist: numpy (>=1.14.1)
